Petstore/__init__.py
Petstore/client.py
Petstore/core/__init__.py
Petstore/core/api_error.py
Petstore/core/client_wrapper.py
Petstore/core/datetime_utils.py
Petstore/core/jsonable_encoder.py
Petstore/core/remove_none_from_dict.py
Petstore/environment.py
Petstore/errors/__init__.py
Petstore/errors/bad_request_error.py
Petstore/errors/not_found_error.py
Petstore/py.typed
Petstore/resources/__init__.py
Petstore/resources/pet/__init__.py
Petstore/resources/pet/client.py
Petstore/resources/pet/types/__init__.py
Petstore/resources/pet/types/find_pets_by_status_request_status.py
Petstore/resources/store/__init__.py
Petstore/resources/store/client.py
Petstore/resources/user/__init__.py
Petstore/resources/user/client.py
Petstore/types/__init__.py
Petstore/types/address.py
Petstore/types/api_response.py
Petstore/types/category.py
Petstore/types/customer.py
Petstore/types/oauth_scope.py
Petstore/types/order.py
Petstore/types/order_status.py
Petstore/types/pet.py
Petstore/types/pet_status.py
Petstore/types/tag.py
Petstore/types/user.py
petstore-0.0.3.dist-info/METADATA
petstore-0.0.3.dist-info/WHEEL
petstore-0.0.3.dist-info/RECORD
